ascii_img/__init__.py
ascii_img/ascii_img.py
ascii_img-0.1.0.dist-info/LICENSE
ascii_img-0.1.0.dist-info/METADATA
ascii_img-0.1.0.dist-info/WHEEL
ascii_img-0.1.0.dist-info/entry_points.txt
ascii_img-0.1.0.dist-info/top_level.txt
ascii_img-0.1.0.dist-info/RECORD
